{
  "meta": {
    "updated": "2026-07-14 11:14 UTC",
    "source": "AISStream"
  },
  "summary": {
    "tracked_tankers": 116,
    "in_hormuz": 0,
    "in_suez": 2,
    "in_bab_el_mandeb": 0,
    "in_bosporus": 1
  },
  "vessels": [
    {
      "name": "DORIN",
      "mmsi": 613414203,
      "imo": 9290828,
      "ship_type": 80,
      "lat": 31.52369333333333,
      "lon": 32.25694333333333,
      "speed": 0.1,
      "course": 125.1,
      "heading": 308,
      "destination": "PORT_SAID",
      "zone": "suez"
    },
    {
      "name": "WOLF 1",
      "mmsi": 271054147,
      "imo": 1109683,
      "ship_type": 80,
      "lat": 40.96740833333333,
      "lon": 28.970921666666666,
      "speed": 10.3,
      "course": 146.8,
      "heading": 141,
      "destination": "ISTANBUL",
      "zone": "bosporus"
    },
    {
      "name": "YM NEPTUNE",
      "mmsi": 249813000,
      "imo": 9464106,
      "ship_type": 80,
      "lat": 31.345758333333333,
      "lon": 32.33701833333333,
      "speed": 0,
      "course": 347,
      "heading": 296,
      "destination": "EGEDK>EGPSD",
      "zone": "suez"
    },
    {
      "name": "AEGEAN TIFFANY",
      "mmsi": 240870000,
      "imo": 9314478,
      "ship_type": 80,
      "lat": 38.037058333333334,
      "lon": 23.533268333333336,
      "speed": 0,
      "course": 28.8,
      "heading": 0,
      "destination": "PERIOXH",
      "zone": "other"
    },
    {
      "name": "AEGEAN VIII",
      "mmsi": 240732000,
      "imo": 8817576,
      "ship_type": 80,
      "lat": 38.22688333333333,
      "lon": 21.718813333333333,
      "speed": 0,
      "course": 0.1,
      "heading": 3,
      "destination": "GRPIR",
      "zone": "other"
    },
    {
      "name": "AEGEAN WINNER",
      "mmsi": 241964000,
      "imo": 1042524,
      "ship_type": 80,
      "lat": 38.211655,
      "lon": 15.269338333333334,
      "speed": 0,
      "course": 147.8,
      "heading": 11,
      "destination": "ITMLZ",
      "zone": "other"
    },
    {
      "name": "AGAMEMNON",
      "mmsi": 207133000,
      "imo": 6817857,
      "ship_type": 80,
      "lat": 43.18921,
      "lon": 27.914056666666667,
      "speed": 0,
      "course": 0,
      "heading": 511,
      "destination": "VARNA",
      "zone": "other"
    },
    {
      "name": "AIN ZEFT",
      "mmsi": 605076180,
      "imo": 9265380,
      "ship_type": 81,
      "lat": 37.2183,
      "lon": 15.202016666666667,
      "speed": 0,
      "course": 141.6,
      "heading": 141,
      "destination": "IT AUG",
      "zone": "other"
    },
    {
      "name": "ALANGOVA",
      "mmsi": 271002559,
      "imo": 9411927,
      "ship_type": 80,
      "lat": 36.544845,
      "lon": -3.6473866666666668,
      "speed": 11.8,
      "course": 101.1,
      "heading": 101,
      "destination": "MTMLA",
      "zone": "other"
    },
    {
      "name": "ALATEPE",
      "mmsi": 271044357,
      "imo": 9104873,
      "ship_type": 80,
      "lat": 38.272558333333336,
      "lon": 21.64020833333333,
      "speed": 12,
      "course": 65.3,
      "heading": 68,
      "destination": "EGPSD",
      "zone": "other"
    },
    {
      "name": "ALEXANDRA G",
      "mmsi": 240752600,
      "imo": 9555591,
      "ship_type": 80,
      "lat": 37.961843333333334,
      "lon": 23.567675,
      "speed": 0,
      "course": 349,
      "heading": 511,
      "destination": "PIRAEUS",
      "zone": "other"
    },
    {
      "name": "AMAZONITH",
      "mmsi": 210688000,
      "imo": 929347800,
      "ship_type": 82,
      "lat": 41.89318,
      "lon": 11.166816666666668,
      "speed": 9.3,
      "course": 301,
      "heading": 300,
      "destination": "IT LIV",
      "zone": "other"
    },
    {
      "name": "APTERA",
      "mmsi": 241654000,
      "imo": 9036868,
      "ship_type": 80,
      "lat": 37.95667666666667,
      "lon": 23.595973333333333,
      "speed": 0,
      "course": 66.2,
      "heading": 347,
      "destination": "GRPIR",
      "zone": "other"
    },
    {
      "name": "AQUILA L",
      "mmsi": 636018640,
      "imo": 9829411,
      "ship_type": 80,
      "lat": 36.166961666666666,
      "lon": -3.3364566666666664,
      "speed": 14,
      "course": 85.2,
      "heading": 79,
      "destination": "TR GEB",
      "zone": "other"
    },
    {
      "name": "ARCHON MICHAIL",
      "mmsi": 240043800,
      "imo": 8421365,
      "ship_type": 80,
      "lat": 37.95962833333333,
      "lon": 23.606578333333335,
      "speed": 0,
      "course": 360,
      "heading": 511,
      "destination": "PERIOHI",
      "zone": "other"
    },
    {
      "name": "ATLANTIC  MATE",
      "mmsi": 236683000,
      "imo": 9350745,
      "ship_type": 80,
      "lat": 35.80968666666667,
      "lon": -4.414048333333333,
      "speed": 0.2,
      "course": 309.4,
      "heading": 217,
      "destination": "FOR ORDERS",
      "zone": "other"
    },
    {
      "name": "AURORA",
      "mmsi": 668116291,
      "imo": 9258351,
      "ship_type": 80,
      "lat": 35.9,
      "lon": -4.991361666666666,
      "speed": 0.1,
      "course": 90,
      "heading": 90,
      "destination": "EG PSD",
      "zone": "other"
    },
    {
      "name": "AVENIR ASPIRATION",
      "mmsi": 215902000,
      "imo": 9868962,
      "ship_type": 80,
      "lat": 36.296635,
      "lon": -4.68855,
      "speed": 1,
      "course": 215.7,
      "heading": 225,
      "destination": "ESALG",
      "zone": "other"
    },
    {
      "name": "BARCELONA SPIRIT",
      "mmsi": 311000437,
      "imo": 9578634,
      "ship_type": 80,
      "lat": 45.62804833333333,
      "lon": 13.6773,
      "speed": 0,
      "course": 28.7,
      "heading": 268,
      "destination": "TRIESTE",
      "zone": "other"
    },
    {
      "name": "BAUSTELLA",
      "mmsi": 477103600,
      "imo": 9812133,
      "ship_type": 80,
      "lat": 37.858423333333334,
      "lon": 23.338076666666666,
      "speed": 11.8,
      "course": 102.4,
      "heading": 104,
      "destination": "GR AGT",
      "zone": "other"
    },
    {
      "name": "BELLINI",
      "mmsi": 538005358,
      "imo": 9351440,
      "ship_type": 80,
      "lat": 45.57968166666667,
      "lon": 13.531253333333332,
      "speed": 8.2,
      "course": 55,
      "heading": 55,
      "destination": "ITTRS",
      "zone": "other"
    },
    {
      "name": "BREZZAMARE",
      "mmsi": 247287200,
      "imo": 9479620,
      "ship_type": 80,
      "lat": 44.405923333333334,
      "lon": 8.888713333333333,
      "speed": 0,
      "course": 172.8,
      "heading": 354,
      "destination": "ITGOA",
      "zone": "other"
    },
    {
      "name": "BW YUSHI",
      "mmsi": 563101300,
      "imo": 9810044,
      "ship_type": 80,
      "lat": 35.982925,
      "lon": -4.576251666666667,
      "speed": 3.2,
      "course": 265.4,
      "heading": 253,
      "destination": "ESCEU",
      "zone": "other"
    },
    {
      "name": "CAESAR",
      "mmsi": 636018234,
      "imo": 9235696,
      "ship_type": 80,
      "lat": 34.483475,
      "lon": 33.38467,
      "speed": 2.3,
      "course": 254.7,
      "heading": 236,
      "destination": "OPL CYPRUS",
      "zone": "other"
    },
    {
      "name": "CAPRI",
      "mmsi": 636025443,
      "imo": 9528392,
      "ship_type": 80,
      "lat": 35.723904999999995,
      "lon": -4.906398333333333,
      "speed": 0.5,
      "course": 337.6,
      "heading": 237,
      "destination": "MAPTM",
      "zone": "other"
    },
    {
      "name": "CESARE",
      "mmsi": 247223400,
      "imo": 7041338,
      "ship_type": 80,
      "lat": 40.84314,
      "lon": 14.274638333333334,
      "speed": 0,
      "course": 0,
      "heading": 511,
      "destination": "ITNAP",
      "zone": "other"
    },
    {
      "name": "CHEMICAL RANGER",
      "mmsi": 538010423,
      "imo": 9940746,
      "ship_type": 80,
      "lat": 36.221333333333334,
      "lon": 15.918183333333333,
      "speed": 10.5,
      "course": 91.2,
      "heading": 93,
      "destination": "BEANR",
      "zone": "other"
    },
    {
      "name": "CS ZHE JIANG",
      "mmsi": 477745600,
      "imo": 9899478,
      "ship_type": 80,
      "lat": 35.56031333333333,
      "lon": 16.440906666666667,
      "speed": 12.9,
      "course": 280.5,
      "heading": 280,
      "destination": "MT MLA",
      "zone": "other"
    },
    {
      "name": "CUMBIA 1",
      "mmsi": 538009882,
      "imo": 9436343,
      "ship_type": 80,
      "lat": 36.212985,
      "lon": -4.249638333333333,
      "speed": 2.2,
      "course": 109.9,
      "heading": 199,
      "destination": "ESALG>GIGIB",
      "zone": "other"
    },
    {
      "name": "DELPHI",
      "mmsi": 636014336,
      "imo": 9283796,
      "ship_type": 83,
      "lat": 34.858225,
      "lon": 35.353550000000006,
      "speed": 8.3,
      "course": 215.4,
      "heading": 219,
      "destination": "GR PIR",
      "zone": "other"
    },
    {
      "name": "DELTA BLUE",
      "mmsi": 636021700,
      "imo": 9601235,
      "ship_type": 80,
      "lat": 36.11138166666667,
      "lon": -5.018715,
      "speed": 0.4,
      "course": 332,
      "heading": 255,
      "destination": "THAILAND",
      "zone": "other"
    },
    {
      "name": "DOLPHIN 08",
      "mmsi": 352003628,
      "imo": 9298351,
      "ship_type": 80,
      "lat": 40.703586666666666,
      "lon": 18.764795,
      "speed": 1.4,
      "course": 143.3,
      "heading": 63,
      "destination": "TPA",
      "zone": "other"
    },
    {
      "name": "EASTERLY BIRDIE",
      "mmsi": 538003667,
      "imo": 9423724,
      "ship_type": 80,
      "lat": 32.967216666666666,
      "lon": 32.09683333333333,
      "speed": 0.6,
      "course": 108,
      "heading": 144,
      "destination": "FOR_ORDERS",
      "zone": "other"
    },
    {
      "name": "ELBA",
      "mmsi": 247272700,
      "imo": 9487744,
      "ship_type": 82,
      "lat": 43.557766666666666,
      "lon": 10.296233333333333,
      "speed": 0,
      "course": 22,
      "heading": 45,
      "destination": "IT LIV",
      "zone": "other"
    },
    {
      "name": "EQUALITY",
      "mmsi": 636024924,
      "imo": 1068358,
      "ship_type": 81,
      "lat": 41.30450666666666,
      "lon": 2.198153333333333,
      "speed": 0,
      "course": 324.6,
      "heading": 142,
      "destination": "BARCELONA,SPAIN",
      "zone": "other"
    },
    {
      "name": "ERATO",
      "mmsi": 241324000,
      "imo": 8105088,
      "ship_type": 80,
      "lat": 37.956625,
      "lon": 23.59979333333333,
      "speed": 0,
      "course": 129.5,
      "heading": 511,
      "destination": "GRPIR",
      "zone": "other"
    },
    {
      "name": "ETERNAL",
      "mmsi": 636025354,
      "imo": 9273351,
      "ship_type": 80,
      "lat": 37.582676666666664,
      "lon": 6.816136666666667,
      "speed": 10.5,
      "course": 265,
      "heading": 264,
      "destination": "GR PIR",
      "zone": "other"
    },
    {
      "name": "EVER VIGOROUS",
      "mmsi": 636023607,
      "imo": 9294288,
      "ship_type": 82,
      "lat": 41.333378333333336,
      "lon": 2.1503116666666666,
      "speed": 0,
      "course": 310.9,
      "heading": 27,
      "destination": "ESBCN",
      "zone": "other"
    },
    {
      "name": "GIGLIO",
      "mmsi": 247284200,
      "imo": 9365207,
      "ship_type": 80,
      "lat": 43.58439833333333,
      "lon": 10.319421666666667,
      "speed": 0,
      "course": 75.5,
      "heading": 193,
      "destination": "IT MDC",
      "zone": "other"
    },
    {
      "name": "HAIGUI",
      "mmsi": 636019141,
      "imo": 9505821,
      "ship_type": 80,
      "lat": 37.20666166666667,
      "lon": 15.204975,
      "speed": 0,
      "course": 129.2,
      "heading": 148,
      "destination": "IT AUG",
      "zone": "other"
    },
    {
      "name": "HAUGESUND KNUTSEN",
      "mmsi": 224882000,
      "imo": 9918767,
      "ship_type": 80,
      "lat": 41.308798333333336,
      "lon": 2.1658049999999998,
      "speed": 0,
      "course": 82.7,
      "heading": 36,
      "destination": "ESBCN",
      "zone": "other"
    },
    {
      "name": "HENNING MAERSK",
      "mmsi": 219277000,
      "imo": 9389526,
      "ship_type": 80,
      "lat": 36.97974,
      "lon": 2.09353,
      "speed": 12.1,
      "course": 76.8,
      "heading": 77,
      "destination": "ESGIJ",
      "zone": "other"
    },
    {
      "name": "HISTRIA NARVI",
      "mmsi": 256945000,
      "imo": 9800829,
      "ship_type": 84,
      "lat": 34.69997,
      "lon": 33.345153333333336,
      "speed": 0,
      "course": 360,
      "heading": 243,
      "destination": "CYVAS",
      "zone": "other"
    },
    {
      "name": "HISTRIA PRINCE",
      "mmsi": 538003431,
      "imo": 9436666,
      "ship_type": 80,
      "lat": 42.278303333333334,
      "lon": 9.85361,
      "speed": 11.1,
      "course": 354.6,
      "heading": 353,
      "destination": "GENOA",
      "zone": "other"
    },
    {
      "name": "IEVOLI SHINE",
      "mmsi": 247326000,
      "imo": 9172167,
      "ship_type": 82,
      "lat": 40.78916666666667,
      "lon": 18.323998333333336,
      "speed": 12.9,
      "course": 151,
      "heading": 150,
      "destination": "ITFAL",
      "zone": "other"
    },
    {
      "name": "IONIC ALTHEA",
      "mmsi": 538007953,
      "imo": 9728435,
      "ship_type": 80,
      "lat": 44.36298333333333,
      "lon": 8.863131666666668,
      "speed": 0.1,
      "course": 69.8,
      "heading": 127,
      "destination": "GIGIB>ITGOA",
      "zone": "other"
    },
    {
      "name": "JAXSON",
      "mmsi": 636025571,
      "imo": 9399868,
      "ship_type": 80,
      "lat": 35.670721666666665,
      "lon": -4.876728333333333,
      "speed": 0.4,
      "course": 340,
      "heading": 310,
      "destination": "MA PTM",
      "zone": "other"
    },
    {
      "name": "JEWEL",
      "mmsi": 374987000,
      "imo": 9419450,
      "ship_type": 80,
      "lat": 36.153915,
      "lon": -4.0001,
      "speed": 12.6,
      "course": 82.7,
      "heading": 77,
      "destination": "WAITING ORDER",
      "zone": "other"
    },
    {
      "name": "KILSTRAUM",
      "mmsi": 257643000,
      "imo": 9164732,
      "ship_type": 82,
      "lat": 41.336149999999996,
      "lon": 2.1521666666666666,
      "speed": 0,
      "course": 265.8,
      "heading": 24,
      "destination": "ESBCN",
      "zone": "other"
    },
    {
      "name": "KINISIS",
      "mmsi": 636018011,
      "imo": 9785158,
      "ship_type": 80,
      "lat": 36.23003333333334,
      "lon": -4.900218333333333,
      "speed": 2.1,
      "course": 25.6,
      "heading": 144,
      "destination": "GI GIB- USFPO",
      "zone": "other"
    },
    {
      "name": "KOSOVA",
      "mmsi": 352005315,
      "imo": 9323792,
      "ship_type": 80,
      "lat": 33.93665166666667,
      "lon": 35.30358666666667,
      "speed": 13.6,
      "course": 90.7,
      "heading": 93,
      "destination": "FOR ORDERS",
      "zone": "other"
    },
    {
      "name": "KRITI ROCK",
      "mmsi": 636019277,
      "imo": 9392315,
      "ship_type": 80,
      "lat": 39.457406666666664,
      "lon": 19.436601666666665,
      "speed": 12.6,
      "course": 338,
      "heading": 340,
      "destination": "GRJSY",
      "zone": "other"
    },
    {
      "name": "LANIKAI",
      "mmsi": 311002105,
      "imo": 9240897,
      "ship_type": 80,
      "lat": 37.22338666666667,
      "lon": 15.606533333333335,
      "speed": 0.8,
      "course": 83,
      "heading": 298,
      "destination": "AUGUSTA OPL",
      "zone": "other"
    },
    {
      "name": "MARALTA",
      "mmsi": 305255000,
      "imo": 9324320,
      "ship_type": 80,
      "lat": 31.884400000000003,
      "lon": 31.639433333333333,
      "speed": 0.1,
      "course": 77,
      "heading": 282,
      "destination": "MALTA",
      "zone": "other"
    },
    {
      "name": "MED ATLANTIC",
      "mmsi": 215371000,
      "imo": 9410533,
      "ship_type": 82,
      "lat": 37.19443666666667,
      "lon": 15.211045,
      "speed": 0,
      "course": 237,
      "heading": 126,
      "destination": "MTMLA",
      "zone": "other"
    },
    {
      "name": "MED EMRE",
      "mmsi": 215402000,
      "imo": 9461910,
      "ship_type": 80,
      "lat": 38.03067333333333,
      "lon": 15.5454,
      "speed": 12,
      "course": 194.3,
      "heading": 196,
      "destination": "ITTAR",
      "zone": "other"
    },
    {
      "name": "MED PAKIZE",
      "mmsi": 215486000,
      "imo": 9830604,
      "ship_type": 80,
      "lat": 35.98139833333333,
      "lon": -5.023806666666667,
      "speed": 13.4,
      "course": 80,
      "heading": 86,
      "destination": "TNLGN",
      "zone": "other"
    },
    {
      "name": "MELORIA",
      "mmsi": 247171100,
      "imo": 9292280,
      "ship_type": 80,
      "lat": 38.21693666666667,
      "lon": 15.263731666666667,
      "speed": 3.5,
      "course": 16.1,
      "heading": 23,
      "destination": "IT NAP",
      "zone": "other"
    },
    {
      "name": "MINERVA ALEXANDRA",
      "mmsi": 241734000,
      "imo": 9892999,
      "ship_type": 80,
      "lat": 36.31543,
      "lon": -3.101608333333333,
      "speed": 12.3,
      "course": 261.5,
      "heading": 261,
      "destination": "FOR ORDERS",
      "zone": "other"
    },
    {
      "name": "MINERVA ANNA",
      "mmsi": 636022180,
      "imo": 9298507,
      "ship_type": 80,
      "lat": 36.17019666666667,
      "lon": -4.713838333333333,
      "speed": 5.4,
      "course": 225.3,
      "heading": 226,
      "destination": "FOR ORDERS",
      "zone": "other"
    },
    {
      "name": "MOCHA",
      "mmsi": 613271309,
      "imo": 9271951,
      "ship_type": 80,
      "lat": 35.78035,
      "lon": 16.560355,
      "speed": 10.8,
      "course": 290.7,
      "heading": 290,
      "destination": "AS ORDER",
      "zone": "other"
    },
    {
      "name": "NAVE AMARYLLIS",
      "mmsi": 636026072,
      "imo": 1059644,
      "ship_type": 80,
      "lat": 37.845305,
      "lon": 8.51153,
      "speed": 13.9,
      "course": 260,
      "heading": 258,
      "destination": "ES BIO",
      "zone": "other"
    },
    {
      "name": "NAVIG8 ESTELLE",
      "mmsi": 563258100,
      "imo": 9973925,
      "ship_type": 82,
      "lat": 36.23658666666667,
      "lon": -4.913833333333333,
      "speed": 3.6,
      "course": 244.4,
      "heading": 223,
      "destination": "TRTGT>>GIGIB",
      "zone": "other"
    },
    {
      "name": "NAVIGATOR VIRGO",
      "mmsi": 636015941,
      "imo": 9404819,
      "ship_type": 80,
      "lat": 36.180283333333335,
      "lon": 16.42289166666667,
      "speed": 12.8,
      "course": 272,
      "heading": 272,
      "destination": "ALVOA>GRGYT",
      "zone": "other"
    },
    {
      "name": "NISSOS KOUFONISSI",
      "mmsi": 538008918,
      "imo": 9895214,
      "ship_type": 80,
      "lat": 37.11604166666667,
      "lon": 15.266975,
      "speed": 0,
      "course": 348.2,
      "heading": 50,
      "destination": "SANTA PANAGIA ITALY",
      "zone": "other"
    },
    {
      "name": "NQ LILIUM",
      "mmsi": 249209000,
      "imo": 9393395,
      "ship_type": 82,
      "lat": 41.318999999999996,
      "lon": 2.181833333333333,
      "speed": 0.2,
      "course": 51,
      "heading": 140,
      "destination": "ESBCN",
      "zone": "other"
    },
    {
      "name": "OCEAN WAVE I",
      "mmsi": 352146000,
      "imo": 9356763,
      "ship_type": 80,
      "lat": 35.670445,
      "lon": -4.8241950000000005,
      "speed": 4.3,
      "course": 93.4,
      "heading": 101,
      "destination": "MED.FOR ORDERS",
      "zone": "other"
    },
    {
      "name": "OCEANIC MOON",
      "mmsi": 636023107,
      "imo": 9447809,
      "ship_type": 81,
      "lat": 35.983138333333336,
      "lon": -4.576581666666667,
      "speed": 3.2,
      "course": 265.1,
      "heading": 253,
      "destination": "CEUTA OPL",
      "zone": "other"
    },
    {
      "name": "ORION GAUGUIN",
      "mmsi": 636023761,
      "imo": 9947639,
      "ship_type": 80,
      "lat": 36.64823166666667,
      "lon": -0.43043166666666666,
      "speed": 17.2,
      "course": 261.4,
      "heading": 260,
      "destination": "GIBRALTAR",
      "zone": "other"
    },
    {
      "name": "OTTOMANA",
      "mmsi": 249017000,
      "imo": 9299214,
      "ship_type": 80,
      "lat": 34.67401333333333,
      "lon": 33.984875,
      "speed": 11,
      "course": 250.5,
      "heading": 253,
      "destination": "FOR ORDER",
      "zone": "other"
    },
    {
      "name": "PACIFIC SAPPHIRE",
      "mmsi": 538009200,
      "imo": 9893058,
      "ship_type": 80,
      "lat": 36.14356833333333,
      "lon": -4.849573333333334,
      "speed": 2.9,
      "course": 258.8,
      "heading": 256,
      "destination": "ES ALG",
      "zone": "other"
    },
    {
      "name": "PASCO SYLVIE",
      "mmsi": 538012085,
      "imo": 9332066,
      "ship_type": 80,
      "lat": 36.12443333333333,
      "lon": -2.9752333333333336,
      "speed": 14,
      "course": 268,
      "heading": 267,
      "destination": "GIGIB",
      "zone": "other"
    },
    {
      "name": "PEAK SPIRIT",
      "mmsi": 311000279,
      "imo": 9514171,
      "ship_type": 80,
      "lat": 37.368534999999994,
      "lon": 12.069553333333333,
      "speed": 12.8,
      "course": 318.5,
      "heading": 319,
      "destination": "FOR ORDERS",
      "zone": "other"
    },
    {
      "name": "PETROBAY",
      "mmsi": 224115180,
      "imo": 9301172,
      "ship_type": 80,
      "lat": 41.35538333333333,
      "lon": 2.17288,
      "speed": 0,
      "course": 26.5,
      "heading": 205,
      "destination": "BARCELONA",
      "zone": "other"
    },
    {
      "name": "PETROLINA OCEAN",
      "mmsi": 212422000,
      "imo": 946061700,
      "ship_type": 80,
      "lat": 33.83318333333333,
      "lon": 34.010866666666665,
      "speed": 13.4,
      "course": 145,
      "heading": 146,
      "destination": "CYZYY>ILHFA",
      "zone": "other"
    },
    {
      "name": "PING HAI WAN",
      "mmsi": 356503000,
      "imo": 9558579,
      "ship_type": 80,
      "lat": 37.90688166666666,
      "lon": 23.055368333333334,
      "speed": 0,
      "course": 356.3,
      "heading": 123,
      "destination": "FOR ORDER",
      "zone": "other"
    },
    {
      "name": "PROTEUS BOHEMIA",
      "mmsi": 563173900,
      "imo": 9923437,
      "ship_type": 80,
      "lat": 41.775216666666665,
      "lon": 12.121218333333333,
      "speed": 0.1,
      "course": 54,
      "heading": 168,
      "destination": "TGLFW> ITFCO",
      "zone": "other"
    },
    {
      "name": "PS IMABARI",
      "mmsi": 538009715,
      "imo": 9908504,
      "ship_type": 80,
      "lat": 41.33767666666667,
      "lon": 2.166323333333333,
      "speed": 1.9,
      "course": 170,
      "heading": 184,
      "destination": "ESBCN>DZSKI",
      "zone": "other"
    },
    {
      "name": "PUNTA AZZURRA",
      "mmsi": 247077700,
      "imo": 8420347,
      "ship_type": 82,
      "lat": 37.23883333333333,
      "lon": 15.21526,
      "speed": 0,
      "course": 214.5,
      "heading": 511,
      "destination": "AUGUSTA",
      "zone": "other"
    },
    {
      "name": "RAINBOW",
      "mmsi": 304183000,
      "imo": 9302126,
      "ship_type": 80,
      "lat": 37.90712333333333,
      "lon": 23.55438,
      "speed": 0,
      "course": 252.6,
      "heading": 20,
      "destination": "TR IST",
      "zone": "other"
    },
    {
      "name": "RED HORN",
      "mmsi": 248117000,
      "imo": 9402809,
      "ship_type": 81,
      "lat": 35.90692333333333,
      "lon": -5.020968333333333,
      "speed": 1.3,
      "course": 339.3,
      "heading": 230,
      "destination": "MAPTM",
      "zone": "other"
    },
    {
      "name": "RHOURD EL FARES",
      "mmsi": 605076052,
      "imo": 9537044,
      "ship_type": 84,
      "lat": 39.855048333333336,
      "lon": 12.132516666666668,
      "speed": 13.9,
      "course": 63.5,
      "heading": 62,
      "destination": "DZAZW",
      "zone": "other"
    },
    {
      "name": "RITA IEVOLI",
      "mmsi": 247452200,
      "imo": 9846471,
      "ship_type": 80,
      "lat": 37.223621666666666,
      "lon": 15.606433333333333,
      "speed": 0.8,
      "course": 85,
      "heading": 297,
      "destination": "ITAUG",
      "zone": "other"
    },
    {
      "name": "RITI",
      "mmsi": 352002473,
      "imo": 9249075,
      "ship_type": 80,
      "lat": 35.983320000000006,
      "lon": 16.437321666666666,
      "speed": 11.6,
      "course": 90.8,
      "heading": 91,
      "destination": "DAKAR",
      "zone": "other"
    },
    {
      "name": "SALINA M",
      "mmsi": 247324900,
      "imo": 9340910,
      "ship_type": 80,
      "lat": 37.830733333333335,
      "lon": 15.967216666666667,
      "speed": 11.3,
      "course": 270,
      "heading": 270,
      "destination": "IT TAR",
      "zone": "other"
    },
    {
      "name": "SANDVIKEN",
      "mmsi": 226340000,
      "imo": 9803649,
      "ship_type": 80,
      "lat": 45.58472,
      "lon": -1.4545050000000002,
      "speed": 0.2,
      "course": 282.5,
      "heading": 166,
      "destination": "FR AMS",
      "zone": "other"
    },
    {
      "name": "SB BOREA",
      "mmsi": 247431300,
      "imo": 9362839,
      "ship_type": 80,
      "lat": 40.8373,
      "lon": 14.25734,
      "speed": 0,
      "course": 256.2,
      "heading": 287,
      "destination": "NAPOLI",
      "zone": "other"
    },
    {
      "name": "SB FLEGREA",
      "mmsi": 247437300,
      "imo": 9319973,
      "ship_type": 80,
      "lat": 40.836580000000005,
      "lon": 14.289493333333333,
      "speed": 0,
      "course": 190.3,
      "heading": 209,
      "destination": "ITNAP",
      "zone": "other"
    },
    {
      "name": "SEA VALIANT",
      "mmsi": 538009850,
      "imo": 9420629,
      "ship_type": 80,
      "lat": 36.04238,
      "lon": -5.160546666666666,
      "speed": 11.9,
      "course": 98.6,
      "heading": 111,
      "destination": "ITMLZ",
      "zone": "other"
    },
    {
      "name": "SEAGALAXY",
      "mmsi": 477269100,
      "imo": 9847231,
      "ship_type": 80,
      "lat": 36.096685,
      "lon": -4.0393,
      "speed": 11,
      "course": 268.2,
      "heading": 271,
      "destination": "MALTA FOR ORDERS",
      "zone": "other"
    },
    {
      "name": "SEAPRIDE",
      "mmsi": 229365000,
      "imo": 9629562,
      "ship_type": 84,
      "lat": 36.11718666666666,
      "lon": -3.989438333333333,
      "speed": 11.6,
      "course": 269.1,
      "heading": 272,
      "destination": "BEANR",
      "zone": "other"
    },
    {
      "name": "SEASTAR",
      "mmsi": 256702000,
      "imo": 9373656,
      "ship_type": 81,
      "lat": 45.27256333333333,
      "lon": 13.196528333333333,
      "speed": 10.5,
      "course": 345.6,
      "heading": 347,
      "destination": "ITTRS",
      "zone": "other"
    },
    {
      "name": "SEAVEN OCEAN",
      "mmsi": 241013000,
      "imo": 9377834,
      "ship_type": 80,
      "lat": 37.49228333333333,
      "lon": 23.990806666666668,
      "speed": 10.5,
      "course": 144.9,
      "heading": 145,
      "destination": "GR EEU",
      "zone": "other"
    },
    {
      "name": "SEAVIGOUR",
      "mmsi": 249349000,
      "imo": 9774185,
      "ship_type": 80,
      "lat": 36.30008,
      "lon": -0.9310033333333333,
      "speed": 12.6,
      "course": 268.9,
      "heading": 272,
      "destination": "ESTAR",
      "zone": "other"
    },
    {
      "name": "SERENGETI PARK",
      "mmsi": 636023427,
      "imo": 9992579,
      "ship_type": 80,
      "lat": 43.4985,
      "lon": 10.290621666666668,
      "speed": 0.1,
      "course": 135.1,
      "heading": 217,
      "destination": "ITLIV",
      "zone": "other"
    },
    {
      "name": "SHARIFA 5",
      "mmsi": 622120928,
      "imo": 9340594,
      "ship_type": 81,
      "lat": 31.75284333333333,
      "lon": 31.425696666666667,
      "speed": 14.1,
      "course": 90.4,
      "heading": 89,
      "destination": "EG PSD",
      "zone": "other"
    },
    {
      "name": "SOLAR SKYLER",
      "mmsi": 538008706,
      "imo": 9877640,
      "ship_type": 82,
      "lat": 36.063071666666666,
      "lon": -4.771548333333333,
      "speed": 13.1,
      "course": 78.8,
      "heading": 83,
      "destination": "FR BOD",
      "zone": "other"
    },
    {
      "name": "SONGA POLARIS",
      "mmsi": 256325000,
      "imo": 9457749,
      "ship_type": 82,
      "lat": 37.493341666666666,
      "lon": 16.366093333333332,
      "speed": 13,
      "course": 40.4,
      "heading": 41,
      "destination": "ES CAS",
      "zone": "other"
    },
    {
      "name": "SPABUNKER CINCUENTA",
      "mmsi": 224220360,
      "imo": 9398955,
      "ship_type": 82,
      "lat": 41.344699999999996,
      "lon": 2.1507883333333333,
      "speed": 0,
      "course": 318.8,
      "heading": 6,
      "destination": "BARCELONA",
      "zone": "other"
    },
    {
      "name": "SPABUNKER VEINTIDOS",
      "mmsi": 224101930,
      "imo": 0,
      "ship_type": 80,
      "lat": 41.34166666666667,
      "lon": 2.1504016666666668,
      "speed": 0,
      "course": 360,
      "heading": 8,
      "destination": "BARCELONA",
      "zone": "other"
    },
    {
      "name": "SPATHI",
      "mmsi": 636025953,
      "imo": 9321940,
      "ship_type": 80,
      "lat": 37.455095,
      "lon": 23.926783333333333,
      "speed": 0,
      "course": 127,
      "heading": 77,
      "destination": "TR YAL",
      "zone": "other"
    },
    {
      "name": "SPYROS K",
      "mmsi": 636015119,
      "imo": 9565948,
      "ship_type": 80,
      "lat": 38.01593833333333,
      "lon": 23.594741666666668,
      "speed": 0,
      "course": 33.5,
      "heading": 214,
      "destination": "SKARAMANGKAS",
      "zone": "other"
    },
    {
      "name": "STI ACTON",
      "mmsi": 538005405,
      "imo": 9696553,
      "ship_type": 80,
      "lat": 36.59943666666666,
      "lon": 15.562981666666667,
      "speed": 12.5,
      "course": 219.4,
      "heading": 219,
      "destination": "MTMAR",
      "zone": "other"
    },
    {
      "name": "STI COMANDANTE",
      "mmsi": 538005397,
      "imo": 9686857,
      "ship_type": 80,
      "lat": 36.262523333333334,
      "lon": -4.991388333333333,
      "speed": 1.6,
      "course": 357.7,
      "heading": 297,
      "destination": "GI GIB",
      "zone": "other"
    },
    {
      "name": "SUNLIT",
      "mmsi": 356324000,
      "imo": 9340386,
      "ship_type": 80,
      "lat": 37.924015000000004,
      "lon": 23.602221666666665,
      "speed": 2.8,
      "course": 239.9,
      "heading": 258,
      "destination": "PIRAEUS",
      "zone": "other"
    },
    {
      "name": "SWORD GALAXY",
      "mmsi": 538007300,
      "imo": 9673678,
      "ship_type": 80,
      "lat": 36.06301166666666,
      "lon": -5.379798333333333,
      "speed": 3.5,
      "course": 314.3,
      "heading": 316,
      "destination": "ESALG",
      "zone": "other"
    },
    {
      "name": "TAGOR",
      "mmsi": 613442790,
      "imo": 9282481,
      "ship_type": 80,
      "lat": 32.45225,
      "lon": 30.301933333333334,
      "speed": 11.8,
      "course": 103.3,
      "heading": 102,
      "destination": "TR IST",
      "zone": "other"
    },
    {
      "name": "THALIA",
      "mmsi": 636015372,
      "imo": 9611541,
      "ship_type": 80,
      "lat": 32.81878666666667,
      "lon": 35.00620166666667,
      "speed": 0,
      "course": 175.8,
      "heading": 165,
      "destination": "HAIFA",
      "zone": "other"
    },
    {
      "name": "THEANOULA",
      "mmsi": 253000181,
      "imo": 9935557,
      "ship_type": 80,
      "lat": 36.245025000000005,
      "lon": -5.029125,
      "speed": 10.1,
      "course": 232.3,
      "heading": 228,
      "destination": "ALGECIRAS",
      "zone": "other"
    },
    {
      "name": "UNDA",
      "mmsi": 636021464,
      "imo": 9511234,
      "ship_type": 80,
      "lat": 41.46293166666667,
      "lon": 8.679331666666666,
      "speed": 10.1,
      "course": 297.1,
      "heading": 298,
      "destination": "FRFOS",
      "zone": "other"
    },
    {
      "name": "VALDARNO",
      "mmsi": 247489300,
      "imo": 9717503,
      "ship_type": 81,
      "lat": 37.86185166666667,
      "lon": 16.201825,
      "speed": 12.4,
      "course": 223.3,
      "heading": 225,
      "destination": "IT MLZ",
      "zone": "other"
    },
    {
      "name": "VULCANELLO M",
      "mmsi": 247245300,
      "imo": 9337779,
      "ship_type": 80,
      "lat": 40.8045,
      "lon": 14.317216666666667,
      "speed": 0,
      "course": 51,
      "heading": 275,
      "destination": "IT NAP",
      "zone": "other"
    },
    {
      "name": "WINDPOWER",
      "mmsi": 352004677,
      "imo": 1016056,
      "ship_type": 80,
      "lat": 45.587361666666666,
      "lon": -1.471195,
      "speed": 0,
      "course": 115.3,
      "heading": 203,
      "destination": "FR BYE",
      "zone": "other"
    },
    {
      "name": "XT WALRUS",
      "mmsi": 636026252,
      "imo": 1105077,
      "ship_type": 80,
      "lat": 33.60221166666667,
      "lon": 29.932468333333336,
      "speed": 13,
      "course": 139.3,
      "heading": 139,
      "destination": "TRYAL",
      "zone": "other"
    },
    {
      "name": "YARA J",
      "mmsi": 620800363,
      "imo": 9221803,
      "ship_type": 80,
      "lat": 40.95629333333333,
      "lon": 28.745308333333334,
      "speed": 0.1,
      "course": 80.6,
      "heading": 347,
      "destination": "ISTANBUL",
      "zone": "other"
    },
    {
      "name": "YM PLUTO",
      "mmsi": 249957000,
      "imo": 9464118,
      "ship_type": 80,
      "lat": 38.882445,
      "lon": 0.5274633333333333,
      "speed": 11.4,
      "course": 321.5,
      "heading": 320,
      "destination": "ESVLC-MAMOH",
      "zone": "other"
    }
  ]
}