{
  "meta": {
    "updated": "2026-05-22 13:18 UTC",
    "source": "AISStream"
  },
  "summary": {
    "tracked_tankers": 117,
    "in_hormuz": 0,
    "in_suez": 0,
    "in_bab_el_mandeb": 0,
    "in_bosporus": 1
  },
  "vessels": [
    {
      "name": "JET X",
      "mmsi": 271051403,
      "imo": 9516600,
      "ship_type": 80,
      "lat": 40.98988166666666,
      "lon": 28.949365,
      "speed": 0.7,
      "course": 142.3,
      "heading": 511,
      "destination": "ISTANBUL",
      "zone": "bosporus"
    },
    {
      "name": "ACCORD",
      "mmsi": 239998600,
      "imo": 8923129,
      "ship_type": 80,
      "lat": 38.0417,
      "lon": 23.5242,
      "speed": 0,
      "course": 279.1,
      "heading": 264,
      "destination": "ELEFSIS",
      "zone": "other"
    },
    {
      "name": "ADVANTAGE LOVE",
      "mmsi": 538006074,
      "imo": 9708552,
      "ship_type": 80,
      "lat": 37.55220333333333,
      "lon": -1.05275,
      "speed": 0,
      "course": 340,
      "heading": 73,
      "destination": "ES CAR",
      "zone": "other"
    },
    {
      "name": "AEGEAN ACE",
      "mmsi": 240897000,
      "imo": 903823200,
      "ship_type": 80,
      "lat": 37.941161666666666,
      "lon": 23.624111666666668,
      "speed": 0,
      "course": 90.1,
      "heading": 511,
      "destination": "PERIOHI",
      "zone": "other"
    },
    {
      "name": "AEGEAN DOLPHIN",
      "mmsi": 240132000,
      "imo": 8008486,
      "ship_type": 80,
      "lat": 38.03004166666666,
      "lon": 23.582741666666667,
      "speed": 0.4,
      "course": 247.9,
      "heading": 157,
      "destination": "PERIOXH",
      "zone": "other"
    },
    {
      "name": "AEGEAN III",
      "mmsi": 240708000,
      "imo": 8817564,
      "ship_type": 83,
      "lat": 38.03754833333333,
      "lon": 23.532953333333335,
      "speed": 0,
      "course": 201.9,
      "heading": 253,
      "destination": "GREEU",
      "zone": "other"
    },
    {
      "name": "AEGEAN TIFFANY",
      "mmsi": 240870000,
      "imo": 9314478,
      "ship_type": 80,
      "lat": 38.254915,
      "lon": 21.736661666666667,
      "speed": 0,
      "course": 129.9,
      "heading": 0,
      "destination": "GRGPA",
      "zone": "other"
    },
    {
      "name": "AEGEAN VIII",
      "mmsi": 240732000,
      "imo": 8817576,
      "ship_type": 80,
      "lat": 38.02870666666667,
      "lon": 23.59408833333333,
      "speed": 0,
      "course": 0.1,
      "heading": 263,
      "destination": "GREEU",
      "zone": "other"
    },
    {
      "name": "AGAMEMNON",
      "mmsi": 207133000,
      "imo": 6817857,
      "ship_type": 80,
      "lat": 43.18921,
      "lon": 27.914036666666668,
      "speed": 0,
      "course": 0,
      "heading": 511,
      "destination": "VARNA",
      "zone": "other"
    },
    {
      "name": "AGIOS NIKOLAOS",
      "mmsi": 237829800,
      "imo": 8739449,
      "ship_type": 80,
      "lat": 37.958645000000004,
      "lon": 23.549873333333334,
      "speed": 6,
      "course": 150.2,
      "heading": 511,
      "destination": "PERIOCHI",
      "zone": "other"
    },
    {
      "name": "AKTEA II OSRV",
      "mmsi": 241794000,
      "imo": 9327516,
      "ship_type": 80,
      "lat": 37.65602166666667,
      "lon": 23.729311666666668,
      "speed": 10.1,
      "course": 111.4,
      "heading": 111,
      "destination": "GREEU",
      "zone": "other"
    },
    {
      "name": "ALEXANDRA G",
      "mmsi": 240752600,
      "imo": 9555591,
      "ship_type": 80,
      "lat": 37.958693333333336,
      "lon": 23.6115,
      "speed": 0,
      "course": 301.9,
      "heading": 511,
      "destination": "PIRAEUS",
      "zone": "other"
    },
    {
      "name": "ALEXANDRIA",
      "mmsi": 210412000,
      "imo": 9448889,
      "ship_type": 80,
      "lat": 34.673845,
      "lon": 33.073593333333335,
      "speed": 0,
      "course": 275.8,
      "heading": 213,
      "destination": "CY LMS",
      "zone": "other"
    },
    {
      "name": "ALLEGRA",
      "mmsi": 247276100,
      "imo": 9436707,
      "ship_type": 84,
      "lat": 45.604974999999996,
      "lon": 13.792488333333333,
      "speed": 0,
      "course": 267.5,
      "heading": 66,
      "destination": "ITTRS",
      "zone": "other"
    },
    {
      "name": "AMILLA  I",
      "mmsi": 237943800,
      "imo": 8739011,
      "ship_type": 80,
      "lat": 37.43224333333333,
      "lon": 24.947368333333333,
      "speed": 0,
      "course": 330.9,
      "heading": 511,
      "destination": "SYROS",
      "zone": "other"
    },
    {
      "name": "ANWAAR ALNASER",
      "mmsi": 642122018,
      "imo": 9313450,
      "ship_type": 80,
      "lat": 41.210633333333334,
      "lon": 19.053271666666667,
      "speed": 0.7,
      "course": 173.7,
      "heading": 256,
      "destination": "AL ROM",
      "zone": "other"
    },
    {
      "name": "APTERA",
      "mmsi": 241654000,
      "imo": 9036868,
      "ship_type": 80,
      "lat": 37.929785,
      "lon": 23.56959833333333,
      "speed": 5.5,
      "course": 223.8,
      "heading": 225,
      "destination": "GRPIR",
      "zone": "other"
    },
    {
      "name": "ARDENZA",
      "mmsi": 247256600,
      "imo": 9377195,
      "ship_type": 80,
      "lat": 38.216499999999996,
      "lon": 15.295166666666667,
      "speed": 0.1,
      "course": 299,
      "heading": 282,
      "destination": "ITMLZ",
      "zone": "other"
    },
    {
      "name": "ARMADALNGMEDITERRANA",
      "mmsi": 249320000,
      "imo": 8125868,
      "ship_type": 81,
      "lat": 35.82778666666666,
      "lon": 14.554115,
      "speed": 0,
      "course": 144,
      "heading": 511,
      "destination": "MARSAXLOKK,MALTA",
      "zone": "other"
    },
    {
      "name": "ASTRAIA",
      "mmsi": 209835000,
      "imo": 9550589,
      "ship_type": 80,
      "lat": 34.673048333333334,
      "lon": 33.08374666666666,
      "speed": 0,
      "course": 99,
      "heading": 207,
      "destination": "LIMASSOL",
      "zone": "other"
    },
    {
      "name": "ATLANTIC",
      "mmsi": 241770000,
      "imo": 9912139,
      "ship_type": 80,
      "lat": 38.23232666666667,
      "lon": 15.323798333333334,
      "speed": 0,
      "course": 1.6,
      "heading": 294,
      "destination": "GIGIB",
      "zone": "other"
    },
    {
      "name": "BELGRAVIA V",
      "mmsi": 538010472,
      "imo": 9341897,
      "ship_type": 84,
      "lat": 41.64979166666667,
      "lon": 41.65249333333334,
      "speed": 0,
      "course": 84.5,
      "heading": 258,
      "destination": "GEBUS",
      "zone": "other"
    },
    {
      "name": "BOLD WARRIOR",
      "mmsi": 636024897,
      "imo": 1058092,
      "ship_type": 80,
      "lat": 37.868590000000005,
      "lon": 23.577158333333333,
      "speed": 2.8,
      "course": 293.4,
      "heading": 296,
      "destination": "GRPIR",
      "zone": "other"
    },
    {
      "name": "BREZZAMARE",
      "mmsi": 247287200,
      "imo": 9479620,
      "ship_type": 80,
      "lat": 44.40318666666667,
      "lon": 8.906975,
      "speed": 0,
      "course": 21.9,
      "heading": 96,
      "destination": "ITGOA",
      "zone": "other"
    },
    {
      "name": "CAPRAIA",
      "mmsi": 247170100,
      "imo": 9304473,
      "ship_type": 84,
      "lat": 43.5557,
      "lon": 10.301473333333332,
      "speed": 0,
      "course": 360,
      "heading": 511,
      "destination": "IT LIV",
      "zone": "other"
    },
    {
      "name": "CESARE",
      "mmsi": 247223400,
      "imo": 7041338,
      "ship_type": 80,
      "lat": 40.84232166666666,
      "lon": 14.263316666666666,
      "speed": 0,
      "course": 0,
      "heading": 511,
      "destination": "ITNAP",
      "zone": "other"
    },
    {
      "name": "CHEMICAL ENTERPRISE",
      "mmsi": 563061100,
      "imo": 9827475,
      "ship_type": 80,
      "lat": 31.71709,
      "lon": 35.9994,
      "speed": 0,
      "course": 217.2,
      "heading": 282,
      "destination": "FRLAV",
      "zone": "other"
    },
    {
      "name": "CHEMICAL LUNA",
      "mmsi": 256154000,
      "imo": 9521423,
      "ship_type": 82,
      "lat": 31.717109999999998,
      "lon": 35.999386666666666,
      "speed": 0.1,
      "course": 153.7,
      "heading": 251,
      "destination": "ILHFA",
      "zone": "other"
    },
    {
      "name": "CHEMICAL SAILOR",
      "mmsi": 249022000,
      "imo": 9804875,
      "ship_type": 82,
      "lat": 42.91439833333333,
      "lon": 9.612036666666667,
      "speed": 12.4,
      "course": 170,
      "heading": 169,
      "destination": "ALIYAGA/TURKEY",
      "zone": "other"
    },
    {
      "name": "CHEMROAD QUEST",
      "mmsi": 371025000,
      "imo": 9451288,
      "ship_type": 82,
      "lat": 37.54685666666667,
      "lon": -0.5241,
      "speed": 12.9,
      "course": 42,
      "heading": 40,
      "destination": "FR LAV",
      "zone": "other"
    },
    {
      "name": "CHERRY TONDA",
      "mmsi": 352003888,
      "imo": 9288942,
      "ship_type": 80,
      "lat": 42.73209666666666,
      "lon": 15.57459,
      "speed": 11.4,
      "course": 316.3,
      "heading": 316,
      "destination": "RAVENNA",
      "zone": "other"
    },
    {
      "name": "DELTA IOS",
      "mmsi": 636022701,
      "imo": 9406685,
      "ship_type": 80,
      "lat": 36.39469999999999,
      "lon": 14.97305,
      "speed": 12,
      "course": 274,
      "heading": 274,
      "destination": "PIRAEUS",
      "zone": "other"
    },
    {
      "name": "DELTA SKY",
      "mmsi": 636014185,
      "imo": 9410181,
      "ship_type": 80,
      "lat": 36.207085,
      "lon": 14.744069999999999,
      "speed": 0.7,
      "course": 115.3,
      "heading": 49,
      "destination": "GENOVA ,ITALY",
      "zone": "other"
    },
    {
      "name": "DENSA DEFNE",
      "mmsi": 229922000,
      "imo": 9297204,
      "ship_type": 80,
      "lat": 38.010795,
      "lon": 23.528315000000003,
      "speed": 0,
      "course": 217.8,
      "heading": 30,
      "destination": "GRASS",
      "zone": "other"
    },
    {
      "name": "DIVINA",
      "mmsi": 247270600,
      "imo": 9377200,
      "ship_type": 81,
      "lat": 38.213325000000005,
      "lon": 12.42936,
      "speed": 10.7,
      "course": 80,
      "heading": 78,
      "destination": "MT MAR",
      "zone": "other"
    },
    {
      "name": "ECO CHIOS",
      "mmsi": 538005496,
      "imo": 9698367,
      "ship_type": 80,
      "lat": 38.027121666666666,
      "lon": 23.59612,
      "speed": 0,
      "course": 24.4,
      "heading": 190,
      "destination": "GR ASS",
      "zone": "other"
    },
    {
      "name": "ECOBREEZE",
      "mmsi": 240871000,
      "imo": 9314466,
      "ship_type": 81,
      "lat": 38.03722166666667,
      "lon": 23.533211666666666,
      "speed": 0,
      "course": 0,
      "heading": 240,
      "destination": "PERIOXI",
      "zone": "other"
    },
    {
      "name": "ECODREAM",
      "mmsi": 239550200,
      "imo": 8865640,
      "ship_type": 81,
      "lat": 38.037805000000006,
      "lon": 23.533255,
      "speed": 0,
      "course": 186.7,
      "heading": 57,
      "destination": "PERIOCHI",
      "zone": "other"
    },
    {
      "name": "EKO2",
      "mmsi": 240827000,
      "imo": 9393955,
      "ship_type": 80,
      "lat": 36.32752,
      "lon": 27.624068333333334,
      "speed": 9.6,
      "course": 50.5,
      "heading": 47,
      "destination": "GRAIG",
      "zone": "other"
    },
    {
      "name": "ELIN POSEIDON",
      "mmsi": 241006000,
      "imo": 9301677,
      "ship_type": 81,
      "lat": 37.73271,
      "lon": 23.719375,
      "speed": 11.4,
      "course": 331,
      "heading": 333,
      "destination": "GRMXK",
      "zone": "other"
    },
    {
      "name": "EMMY SCHULTE",
      "mmsi": 538012458,
      "imo": 9394519,
      "ship_type": 82,
      "lat": 44.39298833333333,
      "lon": 8.87625,
      "speed": 0,
      "course": 82.5,
      "heading": 279,
      "destination": "GENOA",
      "zone": "other"
    },
    {
      "name": "ESKE",
      "mmsi": 249930000,
      "imo": 9479632,
      "ship_type": 80,
      "lat": 39.60106666666666,
      "lon": 0.13666,
      "speed": 8.6,
      "course": 178.9,
      "heading": 179,
      "destination": "ES VLC",
      "zone": "other"
    },
    {
      "name": "EVELPIS",
      "mmsi": 636025154,
      "imo": 9548158,
      "ship_type": 80,
      "lat": 38.020815,
      "lon": 23.54012,
      "speed": 0.1,
      "course": 144.5,
      "heading": 36,
      "destination": "GR ELE",
      "zone": "other"
    },
    {
      "name": "FRONT ANTARES",
      "mmsi": 538007133,
      "imo": 9745926,
      "ship_type": 80,
      "lat": 45.63515333333333,
      "lon": 13.693164999999999,
      "speed": 0,
      "course": 221.3,
      "heading": 266,
      "destination": "ITTRS",
      "zone": "other"
    },
    {
      "name": "GAS SPANAKOPITA",
      "mmsi": 667002512,
      "imo": 9232321,
      "ship_type": 80,
      "lat": 34.551685,
      "lon": 33.414546666666666,
      "speed": 9.5,
      "course": 69.5,
      "heading": 69,
      "destination": "OPL LACONIAN GULF",
      "zone": "other"
    },
    {
      "name": "GAS VITALITY",
      "mmsi": 228403600,
      "imo": 9909285,
      "ship_type": 80,
      "lat": 43.339331666666666,
      "lon": 5.331988333333333,
      "speed": 0,
      "course": 328,
      "heading": 315,
      "destination": "FRFOS",
      "zone": "other"
    },
    {
      "name": "GAZ ENERGY",
      "mmsi": 355238000,
      "imo": 9458169,
      "ship_type": 81,
      "lat": 34.511446666666664,
      "lon": 33.32423333333333,
      "speed": 0.9,
      "course": 87.2,
      "heading": 314,
      "destination": "OPL LIMASSOL",
      "zone": "other"
    },
    {
      "name": "GEMMA",
      "mmsi": 248768000,
      "imo": 9808314,
      "ship_type": 80,
      "lat": 35.82817,
      "lon": 14.55021,
      "speed": 0,
      "course": 98,
      "heading": 199,
      "destination": "ES BCN",
      "zone": "other"
    },
    {
      "name": "GEORGIA G",
      "mmsi": 240620300,
      "imo": 9119464,
      "ship_type": 80,
      "lat": 37.958421666666666,
      "lon": 23.610976666666666,
      "speed": 0,
      "course": 236.2,
      "heading": 511,
      "destination": "PERIOXI",
      "zone": "other"
    },
    {
      "name": "GERANI",
      "mmsi": 241423000,
      "imo": 9435832,
      "ship_type": 80,
      "lat": 37.858575,
      "lon": 23.55498,
      "speed": 7.8,
      "course": 58.3,
      "heading": 57,
      "destination": "AGIOI THEODOROI",
      "zone": "other"
    },
    {
      "name": "GIANNA",
      "mmsi": 352004025,
      "imo": 9428360,
      "ship_type": 80,
      "lat": 34.689721666666664,
      "lon": 33.356045,
      "speed": 0,
      "course": 277.2,
      "heading": 246,
      "destination": "CY VAS",
      "zone": "other"
    },
    {
      "name": "GIGLIO",
      "mmsi": 247284200,
      "imo": 9365207,
      "ship_type": 80,
      "lat": 43.556425,
      "lon": 10.30211,
      "speed": 0,
      "course": 25.6,
      "heading": 215,
      "destination": "IT SPZ",
      "zone": "other"
    },
    {
      "name": "GREEN HEART",
      "mmsi": 249697000,
      "imo": 9507867,
      "ship_type": 80,
      "lat": 37.432215,
      "lon": 24.943841666666668,
      "speed": 0,
      "course": 81.3,
      "heading": 31,
      "destination": "GR JSY",
      "zone": "other"
    },
    {
      "name": "HAFNIA BERING",
      "mmsi": 566255000,
      "imo": 9725603,
      "ship_type": 83,
      "lat": 35.81630833333334,
      "lon": 14.545541666666667,
      "speed": 0,
      "course": 108.4,
      "heading": 46,
      "destination": "GEBUS",
      "zone": "other"
    },
    {
      "name": "HATAY",
      "mmsi": 352003675,
      "imo": 9354258,
      "ship_type": 80,
      "lat": 38.28924166666666,
      "lon": 15.323678333333334,
      "speed": 8.6,
      "course": 25.9,
      "heading": 19,
      "destination": "ITMLZ",
      "zone": "other"
    },
    {
      "name": "HAUGESUND KNUTSEN",
      "mmsi": 224882000,
      "imo": 9918767,
      "ship_type": 80,
      "lat": 41.30882166666667,
      "lon": 2.16576,
      "speed": 0.1,
      "course": 81.6,
      "heading": 35,
      "destination": "ESBCN",
      "zone": "other"
    },
    {
      "name": "HENNING MAERSK",
      "mmsi": 219277000,
      "imo": 9389526,
      "ship_type": 80,
      "lat": 41.309459999999994,
      "lon": 2.18853,
      "speed": 0.1,
      "course": 344.9,
      "heading": 64,
      "destination": "ESBCN",
      "zone": "other"
    },
    {
      "name": "HISTRIA PRINCE",
      "mmsi": 538003431,
      "imo": 9436666,
      "ship_type": 80,
      "lat": 34.68907,
      "lon": 33.33137,
      "speed": 0,
      "course": 130.6,
      "heading": 241,
      "destination": "CYVAS",
      "zone": "other"
    },
    {
      "name": "ICHESIA M",
      "mmsi": 247433700,
      "imo": 9436678,
      "ship_type": 81,
      "lat": 43.55611833333333,
      "lon": 10.292993333333333,
      "speed": 6.3,
      "course": 34,
      "heading": 37,
      "destination": "IT LIV",
      "zone": "other"
    },
    {
      "name": "IMERA",
      "mmsi": 229561000,
      "imo": 9458066,
      "ship_type": 81,
      "lat": 37.348198333333336,
      "lon": -0.878585,
      "speed": 11.9,
      "course": 227,
      "heading": 225,
      "destination": "ES ALG",
      "zone": "other"
    },
    {
      "name": "ISLAND RUBY",
      "mmsi": 210613000,
      "imo": 9578488,
      "ship_type": 80,
      "lat": 34.68026666666666,
      "lon": 33.07333666666667,
      "speed": 0,
      "course": 336.9,
      "heading": 212,
      "destination": "CY LMS",
      "zone": "other"
    },
    {
      "name": "KALLIOPI G",
      "mmsi": 240205400,
      "imo": 9472957,
      "ship_type": 80,
      "lat": 38.03608166666667,
      "lon": 23.511416666666666,
      "speed": 0,
      "course": 48.3,
      "heading": 511,
      "destination": "PIRAEUS",
      "zone": "other"
    },
    {
      "name": "KOHYLI",
      "mmsi": 241675000,
      "imo": 9823651,
      "ship_type": 80,
      "lat": 38.03770833333333,
      "lon": 23.533291666666667,
      "speed": 0,
      "course": 0,
      "heading": 60,
      "destination": null,
      "zone": "other"
    },
    {
      "name": "KRITI ADMIRAL",
      "mmsi": 241751000,
      "imo": 9314870,
      "ship_type": 80,
      "lat": 38.03456166666667,
      "lon": 23.508893333333333,
      "speed": 0,
      "course": 87.9,
      "heading": 358,
      "destination": "GRPIR",
      "zone": "other"
    },
    {
      "name": "KRITI ROCK",
      "mmsi": 636019277,
      "imo": 9392315,
      "ship_type": 80,
      "lat": 38.0246,
      "lon": 23.594216666666668,
      "speed": 0,
      "course": 314,
      "heading": 261,
      "destination": "GRASS",
      "zone": "other"
    },
    {
      "name": "LADY MARIELLA",
      "mmsi": 247430200,
      "imo": 9644433,
      "ship_type": 80,
      "lat": 38.22616666666667,
      "lon": 15.261666666666667,
      "speed": 0.1,
      "course": 179.8,
      "heading": 511,
      "destination": "ITMLZ",
      "zone": "other"
    },
    {
      "name": "LADY RINA",
      "mmsi": 247431600,
      "imo": 9631383,
      "ship_type": 80,
      "lat": 38.220130000000005,
      "lon": 15.308686666666667,
      "speed": 0.3,
      "course": 200.3,
      "heading": 272,
      "destination": "ITMLZ",
      "zone": "other"
    },
    {
      "name": "LEGEND PRESTIGE",
      "mmsi": 374773000,
      "imo": 9773234,
      "ship_type": 80,
      "lat": 43.07360666666667,
      "lon": 4.978496666666667,
      "speed": 8.7,
      "course": 27.1,
      "heading": 28,
      "destination": "FRLAV",
      "zone": "other"
    },
    {
      "name": "LYRIC CAMELLIA",
      "mmsi": 311000359,
      "imo": 973093300,
      "ship_type": 80,
      "lat": 44.14527,
      "lon": 8.600751666666667,
      "speed": 12.2,
      "course": 147.6,
      "heading": 148,
      "destination": "ITTRS",
      "zone": "other"
    },
    {
      "name": "MAGELLAN",
      "mmsi": 538012476,
      "imo": 9725615,
      "ship_type": 80,
      "lat": 37.439605,
      "lon": -0.66305,
      "speed": 11.9,
      "course": 47,
      "heading": 49,
      "destination": "ESCAS",
      "zone": "other"
    },
    {
      "name": "MALBURG",
      "mmsi": 677010400,
      "imo": 9035539,
      "ship_type": 80,
      "lat": 43.10026333333334,
      "lon": 28.32373,
      "speed": 0,
      "course": 82.4,
      "heading": 107,
      "destination": "VARNA OPL",
      "zone": "other"
    },
    {
      "name": "MALTA PROSPERITY",
      "mmsi": 636013383,
      "imo": 9389033,
      "ship_type": 80,
      "lat": 35.95179333333333,
      "lon": 14.819408333333334,
      "speed": 0.7,
      "course": 355.1,
      "heading": 359,
      "destination": "MTMLA",
      "zone": "other"
    },
    {
      "name": "MAYARO",
      "mmsi": 431228000,
      "imo": 9733703,
      "ship_type": 80,
      "lat": 39.449261666666665,
      "lon": -0.30948,
      "speed": 0,
      "course": 50.2,
      "heading": 204,
      "destination": "ES VLC",
      "zone": "other"
    },
    {
      "name": "MED BALTIC",
      "mmsi": 215194000,
      "imo": 9462304,
      "ship_type": 82,
      "lat": 44.24015,
      "lon": 8.919666666666666,
      "speed": 12.2,
      "course": 32,
      "heading": 32,
      "destination": "ITGOA",
      "zone": "other"
    },
    {
      "name": "MRC HATICE ANA",
      "mmsi": 215345000,
      "imo": 9536935,
      "ship_type": 80,
      "lat": 38.46938333333333,
      "lon": 2.130116666666667,
      "speed": 10.9,
      "course": 358,
      "heading": 359,
      "destination": "ESCAR",
      "zone": "other"
    },
    {
      "name": "NAVIGER-1",
      "mmsi": 273342100,
      "imo": 8867143,
      "ship_type": 82,
      "lat": 36.50967333333333,
      "lon": 27.779628333333335,
      "speed": 5,
      "course": 292.5,
      "heading": 289,
      "destination": "TR YLOVA",
      "zone": "other"
    },
    {
      "name": "NINFEA",
      "mmsi": 247174500,
      "imo": 8327583,
      "ship_type": 80,
      "lat": 40.47607666666667,
      "lon": 17.202365,
      "speed": 0,
      "course": 199,
      "heading": 511,
      "destination": "ITTAR",
      "zone": "other"
    },
    {
      "name": "OHIO",
      "mmsi": 311013400,
      "imo": 9417440,
      "ship_type": 80,
      "lat": 45.61165666666667,
      "lon": 13.759601666666667,
      "speed": 5,
      "course": 281,
      "heading": 281,
      "destination": "LY ZAW",
      "zone": "other"
    },
    {
      "name": "PLUTO MOON",
      "mmsi": 636019310,
      "imo": 9784025,
      "ship_type": 80,
      "lat": 39.16037333333334,
      "lon": 1.0699383333333332,
      "speed": 11.6,
      "course": 38.7,
      "heading": 39,
      "destination": "FRFOS",
      "zone": "other"
    },
    {
      "name": "PROMETHEUS ENERGY",
      "mmsi": 538008157,
      "imo": 9801988,
      "ship_type": 80,
      "lat": 37.55438,
      "lon": -1.0298116666666666,
      "speed": 0,
      "course": 183,
      "heading": 54,
      "destination": "ES CAR",
      "zone": "other"
    },
    {
      "name": "PROVIDER",
      "mmsi": 273272770,
      "imo": 9312872,
      "ship_type": 80,
      "lat": 36.05032333333334,
      "lon": 15.178808333333334,
      "speed": 11.6,
      "course": 282.6,
      "heading": 511,
      "destination": "SINGAPORE",
      "zone": "other"
    },
    {
      "name": "PUNTA VERDE",
      "mmsi": 247077500,
      "imo": 8807117,
      "ship_type": 81,
      "lat": 40.47761166666667,
      "lon": 17.198976666666667,
      "speed": 0,
      "course": 0,
      "heading": 511,
      "destination": "TARANTO",
      "zone": "other"
    },
    {
      "name": "PUTERI SAADONG",
      "mmsi": 538010566,
      "imo": 9937945,
      "ship_type": 84,
      "lat": 36.432631666666666,
      "lon": 14.565033333333334,
      "speed": 14.6,
      "course": 108.8,
      "heading": 106,
      "destination": "GRREV",
      "zone": "other"
    },
    {
      "name": "RED OPAL",
      "mmsi": 215270000,
      "imo": 9381512,
      "ship_type": 81,
      "lat": 35.8166,
      "lon": 14.545375,
      "speed": 0,
      "course": 242.7,
      "heading": 46,
      "destination": "ESCAS",
      "zone": "other"
    },
    {
      "name": "ROSE I",
      "mmsi": 636022191,
      "imo": 9376945,
      "ship_type": 80,
      "lat": 37.89698833333333,
      "lon": 23.536175,
      "speed": 0.2,
      "course": 19.1,
      "heading": 146,
      "destination": "GR PIR",
      "zone": "other"
    },
    {
      "name": "SALINA BAY",
      "mmsi": 256487000,
      "imo": 8013118,
      "ship_type": 80,
      "lat": 35.81661999999999,
      "lon": 14.583193333333332,
      "speed": 0.4,
      "course": 220.7,
      "heading": 13,
      "destination": "BA3",
      "zone": "other"
    },
    {
      "name": "SALINA M",
      "mmsi": 247324900,
      "imo": 9340910,
      "ship_type": 80,
      "lat": 38.211483333333334,
      "lon": 15.263616666666667,
      "speed": 0.1,
      "course": 79,
      "heading": 12,
      "destination": "ITMLZ",
      "zone": "other"
    },
    {
      "name": "SANDVIKEN",
      "mmsi": 226340000,
      "imo": 9803649,
      "ship_type": 80,
      "lat": 45.581595,
      "lon": -1.4629433333333333,
      "speed": 0,
      "course": 44.6,
      "heading": 101,
      "destination": "FR DON",
      "zone": "other"
    },
    {
      "name": "SANTA ELENA",
      "mmsi": 248230000,
      "imo": 8125600,
      "ship_type": 80,
      "lat": 35.83873833333334,
      "lon": 14.597041666666666,
      "speed": 0,
      "course": 360,
      "heading": 11,
      "destination": "AREA4",
      "zone": "other"
    },
    {
      "name": "SB BOREA",
      "mmsi": 247431300,
      "imo": 9362839,
      "ship_type": 80,
      "lat": 40.836578333333335,
      "lon": 14.289486666666667,
      "speed": 0,
      "course": 130,
      "heading": 208,
      "destination": "NAPOLI",
      "zone": "other"
    },
    {
      "name": "SEAFRIEND",
      "mmsi": 229407000,
      "imo": 9629574,
      "ship_type": 80,
      "lat": 41.31950500000001,
      "lon": 2.184845,
      "speed": 0,
      "course": 309.9,
      "heading": 32,
      "destination": "ESBCN",
      "zone": "other"
    },
    {
      "name": "SEAGAS MAJOR",
      "mmsi": 636016188,
      "imo": 9135793,
      "ship_type": 83,
      "lat": 34.71160333333333,
      "lon": 33.355645,
      "speed": 0.1,
      "course": 271.7,
      "heading": 230,
      "destination": "CYVAS",
      "zone": "other"
    },
    {
      "name": "SEAVEN GRACE",
      "mmsi": 241843000,
      "imo": 9310214,
      "ship_type": 80,
      "lat": 38.022953333333334,
      "lon": 23.541483333333336,
      "speed": 5.4,
      "course": 345.7,
      "heading": 345,
      "destination": "GRRHO",
      "zone": "other"
    },
    {
      "name": "SEAVEN HOPE",
      "mmsi": 241750000,
      "imo": 9466946,
      "ship_type": 80,
      "lat": 38.028999999999996,
      "lon": 23.59515,
      "speed": 0,
      "course": 314,
      "heading": 260,
      "destination": "GRASS",
      "zone": "other"
    },
    {
      "name": "SEAWAYS MUSE",
      "mmsi": 538011488,
      "imo": 9374301,
      "ship_type": 80,
      "lat": 41.346149999999994,
      "lon": 3.476583333333333,
      "speed": 12.6,
      "course": 223,
      "heading": 224,
      "destination": "ESCEU",
      "zone": "other"
    },
    {
      "name": "SEGWAY",
      "mmsi": 636024576,
      "imo": 1050959,
      "ship_type": 80,
      "lat": 44.422806666666666,
      "lon": 8.834286666666666,
      "speed": 0,
      "course": 18.4,
      "heading": 169,
      "destination": "IT GOA",
      "zone": "other"
    },
    {
      "name": "SEKAVIN PIONEER",
      "mmsi": 210908000,
      "imo": 9350252,
      "ship_type": 84,
      "lat": 39.9214,
      "lon": 0.1277,
      "speed": 6.6,
      "course": 33,
      "heading": 31,
      "destination": "ES VLC",
      "zone": "other"
    },
    {
      "name": "SELENA ATK",
      "mmsi": 271049458,
      "imo": 9902665,
      "ship_type": 80,
      "lat": 42.804905,
      "lon": 6.70247,
      "speed": 9.7,
      "course": 78.2,
      "heading": 78,
      "destination": "ESSVQ > FRFOS",
      "zone": "other"
    },
    {
      "name": "SEVERIN SCHULTE",
      "mmsi": 563232200,
      "imo": 9659115,
      "ship_type": 80,
      "lat": 39.990226666666665,
      "lon": 0.11568166666666667,
      "speed": 0,
      "course": 267.9,
      "heading": 176,
      "destination": "ESCAS",
      "zone": "other"
    },
    {
      "name": "SHENANDOAH TRADER",
      "mmsi": 366525000,
      "imo": 9708760,
      "ship_type": 80,
      "lat": 37.87659166666666,
      "lon": 23.52987166666667,
      "speed": 0.1,
      "course": 37.1,
      "heading": 244,
      "destination": "NUNYA",
      "zone": "other"
    },
    {
      "name": "SKUTEVIKEN",
      "mmsi": 226344000,
      "imo": 9803651,
      "ship_type": 80,
      "lat": 46.15805,
      "lon": -1.2411683333333334,
      "speed": 0,
      "course": 188.3,
      "heading": 188,
      "destination": "FR LPE",
      "zone": "other"
    },
    {
      "name": "SLUGGER",
      "mmsi": 210004055,
      "imo": 9342562,
      "ship_type": 80,
      "lat": 31.717096666666666,
      "lon": 35.99937,
      "speed": 0,
      "course": 140.8,
      "heading": 296,
      "destination": "SEA FOR ORDERS",
      "zone": "other"
    },
    {
      "name": "SPABUNKER TREINTA",
      "mmsi": 224142890,
      "imo": 9296638,
      "ship_type": 80,
      "lat": 39.862183333333334,
      "lon": -0.06798,
      "speed": 0,
      "course": 0,
      "heading": 511,
      "destination": "BURRIANA",
      "zone": "other"
    },
    {
      "name": "STINA KOSAN",
      "mmsi": 565842000,
      "imo": 9374569,
      "ship_type": 84,
      "lat": 39.559729999999995,
      "lon": 0.8005333333333333,
      "speed": 14.9,
      "course": 19.5,
      "heading": 18,
      "destination": "ESTAR",
      "zone": "other"
    },
    {
      "name": "SUCCESS",
      "mmsi": 538003677,
      "imo": 9418133,
      "ship_type": 80,
      "lat": 37.41914833333333,
      "lon": -0.777065,
      "speed": 12.9,
      "course": 228,
      "heading": 228,
      "destination": "ES MOT",
      "zone": "other"
    },
    {
      "name": "SUEZ ENCHANTED",
      "mmsi": 636021924,
      "imo": 9318084,
      "ship_type": 80,
      "lat": 36.272875,
      "lon": 14.653308333333333,
      "speed": 13.1,
      "course": 115.7,
      "heading": 114,
      "destination": "ESALG",
      "zone": "other"
    },
    {
      "name": "SUNLIT",
      "mmsi": 356324000,
      "imo": 9340386,
      "ship_type": 80,
      "lat": 43.719683333333336,
      "lon": 9.262483333333334,
      "speed": 10.7,
      "course": 162,
      "heading": 163,
      "destination": "ES BCN",
      "zone": "other"
    },
    {
      "name": "SYN ZANIA",
      "mmsi": 247231200,
      "imo": 9346938,
      "ship_type": 84,
      "lat": 40.38132333333333,
      "lon": 18.440103333333333,
      "speed": 9.6,
      "course": 329.4,
      "heading": 332,
      "destination": "ITPMA",
      "zone": "other"
    },
    {
      "name": "TALAY",
      "mmsi": 538012025,
      "imo": 9445411,
      "ship_type": 80,
      "lat": 41.650045,
      "lon": 41.65432166666667,
      "speed": 0,
      "course": 337.5,
      "heading": 259,
      "destination": "GEBUS",
      "zone": "other"
    },
    {
      "name": "THEANOULA",
      "mmsi": 253000181,
      "imo": 9935557,
      "ship_type": 80,
      "lat": 38.8891,
      "lon": 3.0606466666666665,
      "speed": 13,
      "course": 102.4,
      "heading": 103,
      "destination": "PALMA DE MALLORCA",
      "zone": "other"
    },
    {
      "name": "TINERFE",
      "mmsi": 255831000,
      "imo": 9498107,
      "ship_type": 80,
      "lat": 39.549405,
      "lon": 2.6368566666666666,
      "speed": 1,
      "course": 76.8,
      "heading": 52,
      "destination": "ES CAR",
      "zone": "other"
    },
    {
      "name": "TOMRIS E",
      "mmsi": 271048139,
      "imo": 9228588,
      "ship_type": 80,
      "lat": 40.95635333333333,
      "lon": 28.758264999999998,
      "speed": 0,
      "course": 53,
      "heading": 339,
      "destination": "ISTANBUL",
      "zone": "other"
    },
    {
      "name": "VERONIKI III",
      "mmsi": 240388000,
      "imo": 8626123,
      "ship_type": 80,
      "lat": 38.03119166666667,
      "lon": 23.594085,
      "speed": 0,
      "course": 315.7,
      "heading": 511,
      "destination": "ASPROPYRGOS",
      "zone": "other"
    },
    {
      "name": "VERONIKI IV",
      "mmsi": 241349000,
      "imo": 9015137,
      "ship_type": 80,
      "lat": 37.788736666666665,
      "lon": 24.346608333333332,
      "speed": 10.9,
      "course": 50.3,
      "heading": 50,
      "destination": "GREEU",
      "zone": "other"
    },
    {
      "name": "VEYSEL VARDAL",
      "mmsi": 352001336,
      "imo": 9079303,
      "ship_type": 80,
      "lat": 41.647259999999996,
      "lon": 41.649210000000004,
      "speed": 0,
      "course": 26.4,
      "heading": 259,
      "destination": "GE BUS",
      "zone": "other"
    },
    {
      "name": "YM NEPTUNE",
      "mmsi": 249813000,
      "imo": 9464106,
      "ship_type": 80,
      "lat": 38.551500000000004,
      "lon": 5.013,
      "speed": 11.9,
      "course": 287.7,
      "heading": 287,
      "destination": "ESCAR>ESVLC",
      "zone": "other"
    },
    {
      "name": "ZEFYROS",
      "mmsi": 240485000,
      "imo": 9324382,
      "ship_type": 80,
      "lat": 38.035203333333335,
      "lon": 23.538643333333333,
      "speed": 0,
      "course": 90,
      "heading": 105,
      "destination": "DRAPETSONA",
      "zone": "other"
    }
  ]
}